taxontabletools2/WFD_tools.py
taxontabletools2/__init__.py
taxontabletools2/__main__.py
taxontabletools2/api_modules.py
taxontabletools2/basic_stats.py
taxontabletools2/default_variables.py
taxontabletools2/diversity_analyses.py
taxontabletools2/load_testing_variables.py
taxontabletools2/ordination_analyses.py
taxontabletools2/read_analyses.py
taxontabletools2/sample_comparison.py
taxontabletools2/start.py
taxontabletools2/table_conversion.py
taxontabletools2/table_processing.py
taxontabletools2/taxon_list_export.py
taxontabletools2/taxonomic_composition.py
taxontabletools2/taxontabletools_2.0.py
taxontabletools2/time_series.py
taxontabletools2/user_preferences.xlsx
taxontabletools2/utilities.py
taxontabletools2/Rscripts/EFI.R
taxontabletools2/Rscripts/diathor.R
taxontabletools2/Rscripts/internal/.DS_Store
taxontabletools2/Rscripts/internal/efiminus.R
taxontabletools2/Rscripts/internal/internal.zip
taxontabletools2/WFD_conversion/.DS_Store
taxontabletools2/WFD_conversion/efi_ecoregions.png
taxontabletools2/WFD_conversion/efi_table.xlsx
taxontabletools2/pages/0 Create Taxon Table.py
taxontabletools2/pages/1 Table processing.py
taxontabletools2/pages/2 Table conversion.py
taxontabletools2/pages/3 Sample comparison.py
taxontabletools2/pages/4 Read proportions.py
taxontabletools2/pages/5 Diversity analyses.py
taxontabletools2/pages/6 Ordination analyses.py
taxontabletools2/pages/7 Time series analyses.py
taxontabletools2/pages/8 API modules.py
taxontabletools2/pages/9 WFD conversion.py
taxontabletools2-2.0.13.dist-info/LICENSE
taxontabletools2-2.0.13.dist-info/METADATA
taxontabletools2-2.0.13.dist-info/WHEEL
taxontabletools2-2.0.13.dist-info/entry_points.txt
taxontabletools2-2.0.13.dist-info/top_level.txt
taxontabletools2-2.0.13.dist-info/RECORD
