Metadata-Version: 2.1
Name: taxontabletools2
Version: 2.0.13
Summary: taxontabletools - A comprehensive, platform-independent graphical user interface software to explore and visualise DNA metabarcoding data
Home-page: https://github.com/pypa/taxontabletools2
Author: Till-Hendrik Macher
Author-email: macher@uni-trier.de
License: MIT
Classifier: Programming Language :: Python :: 3
Classifier: License :: OSI Approved :: MIT License
Classifier: Operating System :: OS Independent
Requires-Python: >=3.10
License-File: LICENSE
Requires-Dist: altair>=5.4.1
Requires-Dist: attrs>=24.2.0
Requires-Dist: blinker>=1.8.2
Requires-Dist: cachetools>=5.5.0
Requires-Dist: contourpy>=1.3.0
Requires-Dist: cycler>=0.12.1
Requires-Dist: et-xmlfile>=1.1.0
Requires-Dist: fonttools>=4.54.1
Requires-Dist: gitdb>=4.0.11
Requires-Dist: gitpython>=3.1.43
Requires-Dist: jinja2>=3.1.4
Requires-Dist: jsonschema>=4.23.0
Requires-Dist: jsonschema-specifications>=2024.10.1
Requires-Dist: kaleido
Requires-Dist: kiwisolver>=1.4.7
Requires-Dist: levenshtein>=0.26.0
Requires-Dist: markdown-it-py>=3.0.0
Requires-Dist: markupsafe>=3.0.1
Requires-Dist: matplotlib>=3.9.2
Requires-Dist: matplotlib-venn>=1.1.1
Requires-Dist: mdurl>=0.1.2
Requires-Dist: narwhals>=1.9.2
Requires-Dist: openpyxl>=3.1.5
Requires-Dist: pillow>=10.4.0
Requires-Dist: plotly>=5.24.1
Requires-Dist: protobuf>=5.28.2
Requires-Dist: psutil>=6.0.0
Requires-Dist: pyarrow>=17.0.0
Requires-Dist: pydeck>=0.9.1
Requires-Dist: pymannkendall>=1.4.3
Requires-Dist: pyparsing>=3.1.4
Requires-Dist: python-dateutil>=2.9.0.post0
Requires-Dist: pytz>=2024.2
Requires-Dist: rapidfuzz>=3.10.0
Requires-Dist: referencing>=0.35.1
Requires-Dist: rich>=13.9.2
Requires-Dist: rpds-py>=0.20.0
Requires-Dist: seqconverter>=3.3.1
Requires-Dist: sequencelib>=2.22.0
Requires-Dist: smmap>=5.0.1
Requires-Dist: stqdm>=0.0.5
Requires-Dist: streamlit>=1.39.0
Requires-Dist: tenacity>=9.0.0
Requires-Dist: toml>=0.10.2
Requires-Dist: tornado>=6.4.1
Requires-Dist: tqdm>=4.66.5
Requires-Dist: update-checker>=0.18.0
Requires-Dist: watchdog>=4.0.2
